pride_colors_plotly/__init__.py
pride_colors_plotly/pride_colors.py
pride_colors_plotly-0.1.0.dist-info/entry_points.txt
pride_colors_plotly-0.1.0.dist-info/LICENSE
pride_colors_plotly-0.1.0.dist-info/WHEEL
pride_colors_plotly-0.1.0.dist-info/METADATA
pride_colors_plotly-0.1.0.dist-info/RECORD
