Metadata-Version: 2.1
Name: pride-colors-plotly
Version: 0.1.0
Summary: PlotLY and matplotlib pride flag color maps and templates to make your plots proud :)
Home-page: https://github.com/pride_colors_plotly/pride_colors_plotly
License: GNU GPL v3.0
Author: pride_colors_plotly
Author-email: elastufka@gmail.com
Requires-Python: >=3.7,<4.0
Classifier: Development Status :: 3 - Alpha
Classifier: Intended Audience :: Developers
Classifier: License :: OSI Approved :: GNU General Public License v3 or later (GPLv3+)
Classifier: License :: Other/Proprietary License
Classifier: Operating System :: OS Independent
Classifier: Programming Language :: Python :: 3
Classifier: Programming Language :: Python :: 3.7
Classifier: Programming Language :: Python :: 3.8
Classifier: Programming Language :: Python :: 3.9
Classifier: Programming Language :: Python :: 3.10
Classifier: Programming Language :: Python :: 3
Classifier: Programming Language :: Python :: 3.7
Classifier: Programming Language :: Python :: 3.8
Classifier: Programming Language :: Python :: 3.9
Classifier: Topic :: Software Development :: Libraries :: Python Modules
Requires-Dist: importlib_metadata (>=4.5.0,<5.0.0); python_version < "3.8"
Requires-Dist: rich (>=10.14.0,<11.0.0)
Requires-Dist: typer[all] (>=0.4.0,<0.5.0)
Project-URL: Repository, https://github.com/pride_colors_plotly/pride_colors_plotly
